[
  {
    "id": "black-jack",
    "name": "Black Jack",
    "image": "/images/black-jack.jpg",
    "module": "/js/black-jack.js"
  },
  {
    "id": "memory-game",
    "name": "Memory Game",
    "image": "/images/memory.png",
    "module": "/js/memory-game.js"
  },
  {
    "id": "snake-game",
    "name": "Snake Game",
    "image": "/images/snake.png",
    "module": "/js/snake-game.js"
  },
  {
    "id": "tic-tac-toe",
    "name": "Tic Tac Toe",
    "image": "/images/tic-tac-toe.png",
    "module": "/js/tic-tac-toe.js"
  },
  {
    "id": "memory-game",
    "name": "Memory Game",
    "image": "/images/memory.png",
    "module": "/js/memory-game.js"
  },
  {
    "id": "snake-game",
    "name": "Snake Game",
    "image": "/images/snake.png",
    "module": "/js/snake-game.js"
  },
  {
    "id": "tic-tac-toe",
    "name": "Tic Tac Toe",
    "image": "/images/tic-tac-toe.png",
    "module": "/js/tic-tac-toe.js"
  },
  {
    "id": "memory-game",
    "name": "Memory Game",
    "image": "/images/memory.png",
    "module": "/js/memory-game.js"
  },
  {
    "id": "snake-game",
    "name": "Snake Game",
    "image": "/images/snake.png",
    "module": "/js/snake-game.js"
  }
]